README.md
setup.py
authorizenet_numbers/__init__.py
authorizenet_numbers.egg-info/PKG-INFO
authorizenet_numbers.egg-info/SOURCES.txt
authorizenet_numbers.egg-info/dependency_links.txt
authorizenet_numbers.egg-info/top_level.txt