Metadata-Version: 1.1
Name: authorizenet-numbers
Version: 1.0
Summary: A library containing test credit card numbers for the Authorize.net API.
Home-page: https://github.com/atwalsh/authorizenet_numbers
Author: Adam Walsh
Author-email: adamtwalsh@gmail.com
License: UNKNOWN
Keywords: authorizenet-numbers authorizenet authorize.net number credit card test
Platform: UNKNOWN
Classifier: Development Status :: 3 - Alpha
Classifier: Intended Audience :: Developers
Classifier: Topic :: Utilities
Classifier: License :: OSI Approved :: MIT License
Classifier: Programming Language :: Python :: 3.6
